quantalyze/__init__.py
quantalyze/quantum_oscillations.py
quantalyze/transport.py
quantalyze/beta/__init__.py
quantalyze/beta/plotting.py
quantalyze/beta/thermometry.py
quantalyze/core/__init__.py
quantalyze/core/constants.py
quantalyze/core/differentiation.py
quantalyze/core/fft.py
quantalyze/core/fitting.py
quantalyze/core/interpolation.py
quantalyze/core/smoothing.py
quantalyze/core/symmetrization.py
quantalyze/core/symmetrize.py
quantalyze-0.1.7.dist-info/METADATA
quantalyze-0.1.7.dist-info/WHEEL
quantalyze-0.1.7.dist-info/licenses/LICENSE
quantalyze-0.1.7.dist-info/RECORD
