Metadata-Version: 2.4
Name: quantalyze
Version: 0.1.7
Summary: Utility functions for analyzing scientific data.
Project-URL: Homepage, https://github.com/jakeayres/Quantalyze
Project-URL: Documentation, https://quantalyze.readthedocs.io/en/latest/
Project-URL: Repository, https://github.com/jakeayres/Quantalyze.git
Project-URL: Issues, https://github.com/jakeayres/Quantalyze/issues
License-Expression: MIT
License-File: LICENSE
Requires-Python: >=3.9
Requires-Dist: matplotlib>=3.9.4
Requires-Dist: mkdocs-material>=9.6.9
Requires-Dist: mkdocstrings-python>=1.16.8
Requires-Dist: numpy>=2.0.2
Requires-Dist: pandas>=2.2.3
Requires-Dist: pytest>=8.3.5
Requires-Dist: scipy>=1.13.1
